simpleprotocol/__init__.py
simpleprotocol/message.py
simpleprotocol/simpleprotocol.py
simpleprotocol/socketwrapper.py
simpleprotocol-1.0.1.dist-info/LICENSE
simpleprotocol-1.0.1.dist-info/METADATA
simpleprotocol-1.0.1.dist-info/WHEEL
simpleprotocol-1.0.1.dist-info/top_level.txt
simpleprotocol-1.0.1.dist-info/RECORD
