Metadata-Version: 2.1
Name: simpleprotocol
Version: 1.0.1
Summary: A package for using a basic protocol socket
Home-page: https://github.com/Chinbob2515/python-simpleprotocol
Author: Ben Hack
Author-email: benjamin.hack@balliol.ox.ac.uk
License: UNKNOWN
Platform: UNKNOWN
Classifier: Programming Language :: Python :: 3
Classifier: License :: OSI Approved :: MIT License
Classifier: Operating System :: OS Independent
Requires-Python: >=3.6
